setup.py
shinkenplugins/__init__.py
shinkenplugins.plugins.influxdb.egg-info/PKG-INFO
shinkenplugins.plugins.influxdb.egg-info/SOURCES.txt
shinkenplugins.plugins.influxdb.egg-info/dependency_links.txt
shinkenplugins.plugins.influxdb.egg-info/entry_points.txt
shinkenplugins.plugins.influxdb.egg-info/namespace_packages.txt
shinkenplugins.plugins.influxdb.egg-info/requires.txt
shinkenplugins.plugins.influxdb.egg-info/top_level.txt
shinkenplugins/plugins/__init__.py
shinkenplugins/plugins/influxdb/Influxdb.py
shinkenplugins/plugins/influxdb/__init__.py
tests/__init__.py
tests/test_check_influxdb.py