Metadata-Version: 1.0
Name: shinkenplugins.plugins.influxdb
Version: 1.0
Summary: check if an influxDB instance is launch and some other metrics ( memory allocated, number of shard, number of point write and number of point per shard)
Home-page: https://github.com/savoirfairelinux/sfl-shinken-plugins
Author: Flavien Peyre
Author-email: flavien.peyre@savoirfairelinux.com
License: GPL3+
Platform: any
